openfeature_provider_hyphen/__init__.py
openfeature_provider_hyphen/cache_client.py
openfeature_provider_hyphen/hooks.py
openfeature_provider_hyphen/hyphen_client.py
openfeature_provider_hyphen/provider.py
openfeature_provider_hyphen/types.py
openfeature_provider_hyphen/utils.py
openfeature_provider_python-1.0.0.dist-info/LICENSE
openfeature_provider_python-1.0.0.dist-info/METADATA
openfeature_provider_python-1.0.0.dist-info/WHEEL
openfeature_provider_python-1.0.0.dist-info/RECORD
